trogon/__init__.py
trogon/argparse.py
trogon/click.py
trogon/constants.py
trogon/detect_run_string.py
trogon/run_command.py
trogon/schemas.py
trogon/trogon.py
trogon/trogon.scss
trogon/typer.py
trogon/widgets/__init__.py
trogon/widgets/about.py
trogon/widgets/command_info.py
trogon/widgets/command_tree.py
trogon/widgets/form.py
trogon/widgets/multiple_choice.py
trogon/widgets/parameter_controls.py
trogon_yapx-0.5.0.dev0.dist-info/METADATA
trogon_yapx-0.5.0.dev0.dist-info/WHEEL
trogon_yapx-0.5.0.dev0.dist-info/RECORD
