Metadata-Version: 2.1
Name: trogon-yapx
Version: 0.5.0.dev0
Summary: Automatically generate a Textual TUI for your Python CLI
Home-page: https://github.com/Textualize/trogon
License: MIT
Author: Donald Mellenbruch
Author-email: hello@Fresh2.dev
Requires-Python: >=3.7,<4.0
Classifier: Development Status :: 4 - Beta
Classifier: Environment :: Console
Classifier: Intended Audience :: Developers
Classifier: Intended Audience :: End Users/Desktop
Classifier: Intended Audience :: Information Technology
Classifier: Intended Audience :: Other Audience
Classifier: License :: OSI Approved :: MIT License
Classifier: Operating System :: MacOS
Classifier: Operating System :: Microsoft :: Windows :: Windows 10
Classifier: Operating System :: Microsoft :: Windows :: Windows 11
Classifier: Operating System :: POSIX :: Linux
Classifier: Programming Language :: Python :: 3
Classifier: Programming Language :: Python :: 3.7
Classifier: Programming Language :: Python :: 3.8
Classifier: Programming Language :: Python :: 3.9
Classifier: Programming Language :: Python :: 3.10
Classifier: Programming Language :: Python :: 3.11
Classifier: Topic :: Software Development :: Documentation
Provides-Extra: click
Provides-Extra: typer
Requires-Dist: click (>=8.0.0) ; extra == "click"
Requires-Dist: textual (>=0.26.0)
Requires-Dist: typer (>=0.9.0) ; extra == "typer"
